setup.py
gopage/__init__.py
gopage/crawler.py
gopage/parser.py
gopage/util.py
gopage.egg-info/PKG-INFO
gopage.egg-info/SOURCES.txt
gopage.egg-info/dependency_links.txt
gopage.egg-info/requires.txt
gopage.egg-info/top_level.txt
gopage.egg-info/zip-safe