Metadata-Version: 1.0
Name: gopage
Version: 2.6.1
Summary: use cache for parser and crawler
Home-page: https://xgeric.github.io
Author: xgeric
Author-email: guxt1994@gmail.com
License: MIT
Keywords: python google crawler
Platform: UNKNOWN
